{"stat.useItem.67":1,"stat.useItem.61":1,"stat.leaveGame":5,"achievement.myst.agebook":6,"stat.killEntity.Ghast":1,"stat.mineBlock.87":23,"stat.craftItem.297":40,"stat.mineBlock.18":4,"stat.killEntity.PigZombie":21,"stat.craftItem.331":54,"stat.mineBlock.17":98,"stat.jump":1214,"stat.swimOneCm":21141,"stat.fallOneCm":32932,"achievement.exploreAllBiomes":{"value":0,"progress":["Boneyard","Magical Forest","Visceral Heap","Undergarden","Plains","Mesa Plateau F M","Beach","Stone Beach","Thicket","Eerie","Forest","Ocean","River","Phantasmagoric Inferno","MushroomIsland","Wetland","Swampland","Hell"]},"achievement.myst.symbol":102059,"stat.useItem.331":93,"stat.craftItem.5":16,"stat.useItem.338":1,"stat.damageTaken":11007,"stat.mineBlock.4":19,"stat.mineBlock.5":16,"stat.mineBlock.3":16,"stat.mineBlock.1":6,"stat.mineBlock.61":1,"stat.mineBlock.67":1,"stat.useItem.54":1,"stat.flyOneCm":753697,"stat.useItem.50":31,"stat.craftItem.112":4,"stat.damageDealt":12679,"stat.useItem.58":36,"stat.useItem.21":7,"stat.craftItem.263":81,"stat.walkOneCm":1275592,"stat.craftItem.265":45,"stat.craftItem.266":23,"stat.craftItem.267":1,"stat.playerKills":3,"stat.craftItem.258":1,"stat.killEntity.Creeper":1,"tconstruct.beginner":4,"stat.craftItem.256":1,"stat.craftItem.257":1,"achievement.mineWood":54,"stat.mineBlock.50":9,"stat.mineBlock.54":1,"stat.craftItem.405":16,"stat.useItem.87":1,"stat.useItem.256":16,"stat.useItem.258":4,"stat.useItem.257":4,"achievement.openInventory":229,"stat.craftItem.42":2,"stat.craftItem.280":32,"achievement.myst.write":5,"stat.mobKills":43,"stat.craftItem.152":7,"stat.useItem.12":1,"stat.deaths":10,"stat.useItem.267":11,"stat.drop":142,"stat.playOneMinute":353692,"stat.craftItem.50":52,"stat.useItem.4":28,"stat.useItem.5":16,"achievement.myst.quinn":1,"stat.killEntity.Zombie":7,"stat.craftItem.306":1,"stat.diveOneCm":8749,"stat.mineBlock.31":7,"stat.craftItem.307":1,"stat.craftItem.308":1,"stat.craftItem.309":1}